LICENSE
MANIFEST.in
README.md
setup.py
varlet/__init__.py
varlet.egg-info/PKG-INFO
varlet.egg-info/SOURCES.txt
varlet.egg-info/dependency_links.txt
varlet.egg-info/not-zip-safe
varlet.egg-info/top_level.txt