Metadata-Version: 1.1
Name: varlet
Version: 0.0.8
Summary: Interactive prompt for variables that should be set at runtime
Home-page: UNKNOWN
Author: Matt Johnson
Author-email: mdj2@pdx.edu
License: UNKNOWN
Platform: UNKNOWN
Classifier: Framework :: Django
